{
  "docId": "HHA-GEOMAG-HERBIVORE-2026",
  "classification": "none",
  "sensitivityActivation": {
    "status": "driver_active",
    "activated": false,
    "headline": "Recent Kp\u22655 forcing in last 14 days; public collar data too stale to test herbivore response."
  },
  "hypothesisTiers": {
    "H1": "weak",
    "H2": "inconclusive",
    "H3": "inconclusive",
    "H4": "inconclusive",
    "H5": "see_anomaly_module"
  },
  "movementSource": "movebank_gps",
  "analysisWindow": {
    "analysisEnd": "2020-05-15",
    "analysisStart90": "2020-02-16",
    "analysisStart30": "2020-04-16",
    "analysisStart14": "2020-05-02",
    "baselineStart": "2019-01-01",
    "collarFirst": "2019-01-01",
    "collarLast": "2020-05-15",
    "calendarEnd": "2026-06-24",
    "collarOverlapsCalendarRecent": false,
    "note": "aligned_to_public_collar_observation_window"
  },
  "calendarWindow": {
    "calendarEnd": "2026-06-24",
    "calendarStart90": "2026-03-27",
    "calendarStart30": "2026-05-26",
    "calendarStart14": "2026-06-11",
    "baselineStart": "2021-06-25"
  },
  "outputs": {
    "inventory": "C:\\Users\\info\\OneDrive\\Desktop\\psw.vibelandia.sing13\\research\\geomagnetic-herbivore\\data\\inventory.json",
    "anomaly_report": "C:\\Users\\info\\OneDrive\\Desktop\\psw.vibelandia.sing13\\research\\geomagnetic-herbivore\\data\\anomaly_report.json",
    "trajectories": "C:\\Users\\info\\OneDrive\\Desktop\\psw.vibelandia.sing13\\research\\geomagnetic-herbivore\\data\\trajectories.csv",
    "figures": "C:\\Users\\info\\OneDrive\\Desktop\\psw.vibelandia.sing13\\research\\geomagnetic-herbivore\\output"
  }
}